etikettierer/__init__.py
etikettierer/ipf-logo.ico
etikettierer/labels.py
etikettierer/printers.py
etikettierer/test_logo.py
etikettierer/utils.py
etikettierer-0.0.1.dist-info/licenses/LICENSE
etikettierer-0.0.1.dist-info/METADATA
etikettierer-0.0.1.dist-info/WHEEL
etikettierer-0.0.1.dist-info/top_level.txt
etikettierer-0.0.1.dist-info/RECORD
