Metadata-Version: 2.4
Name: etikettierer
Version: 0.0.1
Summary: Core label and QR generation utilities with built-in printer support.
Author-email: Enno Henn <henn@ipfdd.de>
License: MIT
Requires-Python: >=3.8
License-File: LICENSE
Requires-Dist: Pillow>=8.0
Requires-Dist: qrcode>=7.3
Requires-Dist: zpl
Requires-Dist: brother-ql
Requires-Dist: pywin32>=305; sys_platform == "win32"
Dynamic: license-file
